zipextimporter.py
py2exe/__init__.py
py2exe/_wapi.py
py2exe/boot_common.py
py2exe/boot_ctypes_com_server.py
py2exe/boot_service.py
py2exe/distutils_buildexe.py
py2exe/dllfinder.py
py2exe/hooks.py
py2exe/icons.py
py2exe/mf3.py
py2exe/mf310.py
py2exe/mf34.py
py2exe/patch_distutils.py
py2exe/pescan.py
py2exe/resources.dll
py2exe/resources.py
py2exe/run-py3.13-win-amd64.exe
py2exe/run_ctypes_dll-py3.13-win-amd64.dll
py2exe/run_w-py3.13-win-amd64.exe
py2exe/runtime.py
py2exe/setup_template.py
py2exe/version.py
py2exe/versioninfo.py
py2exe/vendor/modulefinder.py
py2exe-0.14.0.0.dist-info/licenses/LICENSE.txt
py2exe-0.14.0.0.dist-info/licenses/MIT-License.txt
py2exe-0.14.0.0.dist-info/licenses/MPL2-License.txt
py2exe-0.14.0.0.dist-info/METADATA
py2exe-0.14.0.0.dist-info/WHEEL
py2exe-0.14.0.0.dist-info/top_level.txt
py2exe-0.14.0.0.dist-info/RECORD
