Metadata-Version: 2.4
Name: py2exe
Version: 0.14.0.0
Summary: Build standalone executables for Windows
Home-page: http://www.py2exe.org/
Author: Thomas Heller
Author-email: theller@ctypes.org
Maintainer: Alberto Sottile
Maintainer-email: alby128@gmail.com
License: MIT/X11 OR (MPL 2.0)
Project-URL: Source, https://github.com/py2exe/py2exe
Project-URL: Tracker, https://github.com/py2exe/py2exe/issues
Project-URL: Documentation, https://github.com/py2exe/py2exe/blob/master/docs/py2exe.freeze.md
Platform: Windows
Classifier: Development Status :: 4 - Beta
Classifier: Environment :: Console
Classifier: License :: OSI Approved :: MIT License
Classifier: License :: OSI Approved :: Mozilla Public License 2.0 (MPL 2.0)
Classifier: Operating System :: Microsoft :: Windows
Classifier: Programming Language :: C
Classifier: Programming Language :: Python :: 3
Classifier: Programming Language :: Python :: 3.9
Classifier: Programming Language :: Python :: 3.10
Classifier: Programming Language :: Python :: 3.11
Classifier: Programming Language :: Python :: 3.12
Classifier: Programming Language :: Python :: 3.13
Classifier: Programming Language :: Python :: Implementation :: CPython
Classifier: Topic :: Software Development
Classifier: Topic :: Software Development :: Libraries
Classifier: Topic :: Software Development :: Libraries :: Python Modules
Classifier: Topic :: System :: Software Distribution
Classifier: Topic :: Utilities
Requires-Python: >=3.9, <3.14
License-File: LICENSE.txt
License-File: MIT-License.txt
License-File: MPL2-License.txt
Requires-Dist: cachetools
Requires-Dist: pefile
Dynamic: author
Dynamic: author-email
Dynamic: classifier
Dynamic: description
Dynamic: description-content-type
Dynamic: home-page
Dynamic: license
Dynamic: license-file
Dynamic: maintainer
Dynamic: maintainer-email
Dynamic: platform
Dynamic: project-url
Dynamic: requires-dist
Dynamic: requires-python
Dynamic: summary
